README.md
backuputil.py
setup.py
backuputil.egg-info/PKG-INFO
backuputil.egg-info/SOURCES.txt
backuputil.egg-info/dependency_links.txt
backuputil.egg-info/not-zip-safe
backuputil.egg-info/top_level.txt