Metadata-Version: 1.0
Name: backuputil
Version: 0.1
Summary: Description text
Home-page: https://github.com/tklijnsma/backuputil.git
Author: Thomas Klijnsma
Author-email: tklijnsm@gmail.com
License: BSD 3-Clause License
Platform: UNKNOWN
